inaccel/sklearn/__init__.py
inaccel/sklearn/naive_bayes.py
inaccel/sklearn/cluster/__init__.py
inaccel/sklearn/cluster/_kmeans.py
inaccel/sklearn/linear_model/__init__.py
inaccel/sklearn/linear_model/_logistic.py
inaccel_scikit_learn-0.23.1.5.dist-info/LICENSE
inaccel_scikit_learn-0.23.1.5.dist-info/METADATA
inaccel_scikit_learn-0.23.1.5.dist-info/NOTICE
inaccel_scikit_learn-0.23.1.5.dist-info/WHEEL
inaccel_scikit_learn-0.23.1.5.dist-info/top_level.txt
inaccel_scikit_learn-0.23.1.5.dist-info/zip-safe
inaccel_scikit_learn-0.23.1.5.dist-info/RECORD
