Metadata-Version: 2.1
Name: inaccel-scikit-learn
Version: 0.23.1.5
Summary: InAccel scikit-learn-like package
Home-page: https://docs.inaccel.com
Author: InAccel
Author-email: info@inaccel.com
License: Apache-2.0
Keywords: InAccel Coral,FPGA,inaccel,scikit-learn
Classifier: Development Status :: 5 - Production/Stable
Classifier: License :: OSI Approved :: Apache Software License
Classifier: Operating System :: POSIX :: Linux
Classifier: Programming Language :: Python
Classifier: Programming Language :: Python :: 3
Classifier: Programming Language :: Python :: 3.8
Requires-Python: >=3.8
License-File: LICENSE
License-File: NOTICE
Requires-Dist: coral-api (==2.*)
Requires-Dist: scikit-learn (==0.23.1)
